inifini/__init__.py
inifini/__main__.py
inifini-0.0.0.dist-info/LICENSE
inifini-0.0.0.dist-info/METADATA
inifini-0.0.0.dist-info/WHEEL
inifini-0.0.0.dist-info/entry_points.txt
inifini-0.0.0.dist-info/top_level.txt
inifini-0.0.0.dist-info/RECORD
