Metadata-Version: 2.1
Name: inifini
Version: 0.0.0
Summary: A Python multipurpose framework for building any web-server
Home-page: https://github.com/PlayerG9/inifini
Author: PlayerG9
License: MIT
Project-URL: Author Github, https://github.com/PlayerG9
Project-URL: Homepage, https://github.com/PlayerG9/inifini
Project-URL: Bug Tracker, https://github.com/PlayerG9/inifini/issues
Classifier: Intended Audience :: Developers
Classifier: License :: OSI Approved :: MIT License
Classifier: Natural Language :: English
Classifier: Operating System :: OS Independent
Classifier: Programming Language :: Python :: 3
Classifier: Programming Language :: Python :: 3 :: Only
Classifier: Programming Language :: Python :: 3.7
Classifier: Programming Language :: Python :: 3.8
Classifier: Programming Language :: Python :: 3.9
Classifier: Programming Language :: Python :: 3.10
Classifier: Programming Language :: Python :: 3.11
Classifier: Programming Language :: Python :: 3.12
Classifier: Programming Language :: Python :: 3.13
Classifier: Environment :: Web Environment
Classifier: Topic :: Internet
Classifier: Topic :: Internet :: WWW/HTTP
Classifier: Topic :: Internet :: WWW/HTTP :: HTTP Servers
Requires-Python: >=3.7
License-File: LICENSE
Provides-Extra: all
Requires-Dist: better-exceptions ; extra == 'all'
Provides-Extra: development
Requires-Dist: better-exceptions ; extra == 'development'
